<annotation><filename>ScreenShot20170624at13843AM.jpg</filename><size><width>666</width><height>665</height><depth>3</depth></size><object><name>robot</name><bndbox><xmin>190</xmin><ymin>225</ymin><xmax>539</xmax><ymax>585</ymax></bndbox></object><object><name>blueball</name><bndbox><xmin>329</xmin><ymin>78</ymin><xmax>357</xmax><ymax>108</ymax></bndbox></object><object><name>redball</name><bndbox><xmin>355</xmin><ymin>78</ymin><xmax>383</xmax><ymax>106</ymax></bndbox></object><object><name>redball</name><bndbox><xmin>575</xmin><ymin>126</ymin><xmax>614</xmax><ymax>163</ymax></bndbox></object><object><name>blueball</name><bndbox><xmin>108</xmin><ymin>423</ymin><xmax>169</xmax><ymax>484</ymax></bndbox></object></annotation>